dp_mobility_report/__init__.py
dp_mobility_report/constants.py
dp_mobility_report/dpmreport.py
dp_mobility_report/benchmark/__init__.py
dp_mobility_report/benchmark/b_utils.py
dp_mobility_report/benchmark/benchmarkreport.py
dp_mobility_report/benchmark/preprocessing.py
dp_mobility_report/benchmark/similarity_measures.py
dp_mobility_report/model/__init__.py
dp_mobility_report/model/m_utils.py
dp_mobility_report/model/od_analysis.py
dp_mobility_report/model/overview.py
dp_mobility_report/model/place_analysis.py
dp_mobility_report/model/preprocessing.py
dp_mobility_report/model/section.py
dp_mobility_report/model/user_analysis.py
dp_mobility_report/privacy/__init__.py
dp_mobility_report/privacy/diff_privacy.py
dp_mobility_report/report/__init__.py
dp_mobility_report/report/report.py
dp_mobility_report/report/html/__init__.py
dp_mobility_report/report/html/config_templates.py
dp_mobility_report/report/html/html_utils.py
dp_mobility_report/report/html/od_analysis_templates.py
dp_mobility_report/report/html/overview_templates.py
dp_mobility_report/report/html/place_analysis_templates.py
dp_mobility_report/report/html/templates.py
dp_mobility_report/report/html/user_analysis_templates.py
dp_mobility_report/report/html/html_templates/__init__.py
dp_mobility_report/report/html/html_templates/config_segment.html
dp_mobility_report/report/html/html_templates/dp_info.html
dp_mobility_report/report/html/html_templates/od_analysis_segment.html
dp_mobility_report/report/html/html_templates/od_analysis_segment_benchmark.html
dp_mobility_report/report/html/html_templates/overview_segment.html
dp_mobility_report/report/html/html_templates/overview_segment_benchmark.html
dp_mobility_report/report/html/html_templates/place_analysis_segment.html
dp_mobility_report/report/html/html_templates/place_analysis_segment_benchmark.html
dp_mobility_report/report/html/html_templates/similarity_info.html
dp_mobility_report/report/html/html_templates/similarity_measures.html
dp_mobility_report-0.2.10.dist-info/AUTHORS.rst
dp_mobility_report-0.2.10.dist-info/LICENSE
dp_mobility_report-0.2.10.dist-info/METADATA
dp_mobility_report-0.2.10.dist-info/WHEEL
dp_mobility_report-0.2.10.dist-info/top_level.txt
dp_mobility_report-0.2.10.dist-info/RECORD
