Metadata-Version: 2.1
Name: dp-mobility-report
Version: 0.2.10
Summary: Create a report for mobility data with differential privacy guarantees.
Home-page: https://github.com/FreeMoveProject/dp_mobility_report
Author: Alexandra Kapp
Author-email: alexandra.kapp@htw-berlin.de
License: MIT license
Keywords: dp_mobility_report
Classifier: Development Status :: 2 - Pre-Alpha
Classifier: Intended Audience :: Developers
Classifier: License :: OSI Approved :: MIT License
Classifier: Natural Language :: English
Classifier: Programming Language :: Python :: 3
Classifier: Programming Language :: Python :: 3.8
Requires-Python: >=3.8
License-File: LICENSE
License-File: AUTHORS.rst
Requires-Dist: pathlib
Requires-Dist: datetime
Requires-Dist: diffprivlib
Requires-Dist: folium ==0.12.1.post1
Requires-Dist: haversine
Requires-Dist: Jinja2
Requires-Dist: matplotlib
Requires-Dist: numpy
Requires-Dist: pandarallel
Requires-Dist: pandas
Requires-Dist: pyproj
Requires-Dist: pytest
Requires-Dist: geopandas
Requires-Dist: rtree
Requires-Dist: scipy
Requires-Dist: geojson
Requires-Dist: shapely
Requires-Dist: seaborn
Requires-Dist: setuptools
Requires-Dist: scikit-learn
Requires-Dist: Shapely
Requires-Dist: tqdm
Requires-Dist: typing
Requires-Dist: opencv-python
